e6py_aio/__init__.py
e6py_aio/client.py
e6py_aio/const.py
e6py_aio/errors.py
e6py_aio/http/client.py
e6py_aio/http/endpoints/__init__.py
e6py_aio/http/endpoints/flags.py
e6py_aio/http/endpoints/notes.py
e6py_aio/http/endpoints/pools.py
e6py_aio/http/endpoints/posts.py
e6py_aio/http/endpoints/tags.py
e6py_aio/http/route.py
e6py_aio/mixins.py
e6py_aio/models/__init__.py
e6py_aio/models/flag.py
e6py_aio/models/note.py
e6py_aio/models/pool.py
e6py_aio/models/post.py
e6py_aio/models/tag.py
e6py_aio/utils/converters.py
e6py_aio/utils/hash.py
e6py_aio/utils/serializer.py
e6py_aio-0.1.3.dist-info/LICENSE
e6py_aio-0.1.3.dist-info/WHEEL
e6py_aio-0.1.3.dist-info/METADATA
e6py_aio-0.1.3.dist-info/RECORD
