Metadata-Version: 2.1
Name: e6py-aio
Version: 0.1.3
Summary: An e621 asyncio API wrapper
License: MIT
Author: zevaryx
Author-email: zevaryx@gmail.com
Requires-Python: >=3.10,<4
Classifier: License :: OSI Approved :: MIT License
Classifier: Programming Language :: Python :: 3
Classifier: Programming Language :: Python :: 3.10
Classifier: Programming Language :: Python :: 3.11
Requires-Dist: aiofiles (>=23.2.1,<24.0.0)
Requires-Dist: aiohttp (>=3.8.5,<4.0.0)
Requires-Dist: attrs (>=22.2.0,<23.0.0)
Requires-Dist: sentinel (>=1.0.0,<2.0.0)
